pytojsonschema/__init__.py
pytojsonschema/common.py
pytojsonschema/functions.py
pytojsonschema/jsonschema.py
pytojsonschema/types.py
pytojsonschema-1.11.1.dist-info/LICENSE
pytojsonschema-1.11.1.dist-info/METADATA
pytojsonschema-1.11.1.dist-info/WHEEL
pytojsonschema-1.11.1.dist-info/top_level.txt
pytojsonschema-1.11.1.dist-info/RECORD
